[{"line":2,"elements":[{"start_timestamp":"2023-06-11T10:52:35.730Z","line":3,"name":"TC04 KitapYurdu Cok Satan Edebiyat Kitaplari Yayincilar Secme","description":"","id":"kitapyurdu-cok-satan-edebiyat-kitaplari-yayincilar;tc04-kitapyurdu-cok-satan-edebiyat-kitaplari-yayincilar-secme","type":"scenario","keyword":"Scenario","steps":[{"result":{"duration":9037644900,"status":"passed"},"line":4,"name":"Kullanici \"url\" e gider","match":{"arguments":[{"val":"\"url\"","offset":10}],"location":"stepDefinitions.KitapYurdu_Login_StepDefinition.kullaniciEGider(java.lang.String)"},"keyword":"Given "},{"result":{"duration":3169899100,"status":"passed"},"line":5,"name":"kullanici cok satan kitaplar menusu ustune gelir","match":{"location":"stepDefinitions.CokSatanKitaplar_Hakan_StepDefinition.kullaniciCokSatanKitaplarMenusuUstuneGelir()"},"keyword":"Then "},{"result":{"duration":3015639900,"status":"passed"},"line":6,"name":"3 saniye bekleme yapar","match":{"arguments":[{"val":"3","offset":0}],"location":"stepDefinitions.CokSatanKitaplar_Hakan_StepDefinition.saniyeBeklemeYapar(int)"},"keyword":"And "},{"result":{"duration":2081018100,"status":"passed"},"line":7,"name":"cok satan edebiyat kitaplari linkini tiklar","match":{"location":"stepDefinitions.CokSatanKitaplar_Hakan_StepDefinition.cokSatanEdebiyatKitaplariLinkiniTiklar()"},"keyword":"And "},{"result":{"error_message":"org.openqa.selenium.NoSuchElementException: no such element: Unable to locate element: {\"method\":\"xpath\",\"selector\":\"(//div[@id='faceted-search-group-2']//div[@class='row'])[36]\"}\n  (Session info: MicrosoftEdge=114.0.1823.43)\nFor documentation on this error, please visit: https://selenium.dev/exceptions/#no_such_element\nBuild info: version: '4.8.3', revision: 'e5e76298c3'\nSystem info: os.name: 'Windows 10', os.arch: 'amd64', os.version: '10.0', java.version: '19.0.2'\nDriver info: org.openqa.selenium.edge.EdgeDriver\nCommand: [7974df672ffe2b381680df7801b68227, findElement {using=xpath, value=(//div[@id='faceted-search-group-2']//div[@class='row'])[36]}]\nCapabilities {acceptInsecureCerts: false, browserName: msedge, browserVersion: 114.0.1823.43, ms:edgeOptions: {debuggerAddress: localhost:60468}, msedge: {msedgedriverVersion: 114.0.1823.43 (ef5b3acd8c1d..., userDataDir: C:\\Users\\HAKANB~1.DES\\AppDa...}, networkConnectionEnabled: false, pageLoadStrategy: normal, platformName: WINDOWS, proxy: Proxy(), se:cdp: ws://localhost:60468/devtoo..., se:cdpVersion: 114.0.1823.43, setWindowRect: true, strictFileInteractability: false, timeouts: {implicit: 0, pageLoad: 300000, script: 30000}, unhandledPromptBehavior: dismiss and notify, webauthn:extension:credBlob: true, webauthn:extension:largeBlob: true, webauthn:extension:minPinLength: true, webauthn:extension:prf: true, webauthn:virtualAuthenticators: true}\nSession ID: 7974df672ffe2b381680df7801b68227\r\n\tat java.base/jdk.internal.reflect.DirectConstructorHandleAccessor.newInstance(DirectConstructorHandleAccessor.java:67)\r\n\tat java.base/java.lang.reflect.Constructor.newInstanceWithCaller(Constructor.java:500)\r\n\tat java.base/java.lang.reflect.Constructor.newInstance(Constructor.java:484)\r\n\tat org.openqa.selenium.remote.codec.w3c.W3CHttpResponseCodec.createException(W3CHttpResponseCodec.java:200)\r\n\tat org.openqa.selenium.remote.codec.w3c.W3CHttpResponseCodec.decode(W3CHttpResponseCodec.java:133)\r\n\tat org.openqa.selenium.remote.codec.w3c.W3CHttpResponseCodec.decode(W3CHttpResponseCodec.java:53)\r\n\tat org.openqa.selenium.remote.HttpCommandExecutor.execute(HttpCommandExecutor.java:193)\r\n\tat org.openqa.selenium.remote.service.DriverCommandExecutor.invokeExecute(DriverCommandExecutor.java:183)\r\n\tat org.openqa.selenium.remote.service.DriverCommandExecutor.execute(DriverCommandExecutor.java:158)\r\n\tat org.openqa.selenium.remote.RemoteWebDriver.execute(RemoteWebDriver.java:543)\r\n\tat org.openqa.selenium.remote.ElementLocation$ElementFinder$2.findElement(ElementLocation.java:162)\r\n\tat org.openqa.selenium.remote.ElementLocation.findElement(ElementLocation.java:60)\r\n\tat org.openqa.selenium.remote.RemoteWebDriver.findElement(RemoteWebDriver.java:352)\r\n\tat org.openqa.selenium.remote.RemoteWebDriver.findElement(RemoteWebDriver.java:344)\r\n\tat stepDefinitions.KitapYurdu_Yayimcilar.kullaniciYayinciKategorisindenYayimevleriniSiraylaSecer(KitapYurdu_Yayimcilar.java:19)\r\n\tat ✽.kullanici yayinci kategorisinden yayimevlerini sirayla secer(file:///C:/Users/HakanBatirhan/IdeaProjects/Batch129Cucumber_Practice/src/test/resources/features/directory03/KitapYurdu_ZamanAraligi_Yayincilar.feature:8)\r\n","duration":71695584200,"status":"failed"},"line":8,"name":"kullanici yayinci kategorisinden yayimevlerini sirayla secer","match":{"location":"stepDefinitions.KitapYurdu_Yayimcilar.kullaniciYayinciKategorisindenYayimevleriniSiraylaSecer()"},"keyword":"Then "},{"result":{"duration":997000,"status":"skipped"},"line":9,"name":"kullanici sectigi yayimciya gore goruntulenen kitaplarin degistigini dogrular","match":{"location":"stepDefinitions.KitapYurdu_Yayimcilar.kullaniciSectigiYayimciyaGoreGoruntulenenKitaplarinDegistiginiDogrular()"},"keyword":"And "},{"result":{"status":"skipped"},"line":10,"name":"kullanici goruntulenen kitaplarin sectigi yayimcinin kitaplari oldugunu dogrular","match":{"location":"stepDefinitions.KitapYurdu_Yayimcilar.kullaniciGoruntulenenKitaplarinSectigiYayimcininKitaplariOldugunuDogrular()"},"keyword":"And "}],"tags":[{"name":"@yayimcilar"}]}],"name":"KitapYurdu Cok Satan Edebiyat Kitaplari Yayincilar","description":"","id":"kitapyurdu-cok-satan-edebiyat-kitaplari-yayincilar","keyword":"Feature","uri":"file:src/test/resources/features/directory03/KitapYurdu_ZamanAraligi_Yayincilar.feature","tags":[{"name":"@yayimcilar","type":"Tag","location":{"line":1,"column":1}}]}]